pyicoshift/__init__.py
pyicoshift/functions.py
pyicoshift/pyicoshift.py
pyicoshift/nmrdatatools/__init__.py
pyicoshift/nmrdatatools/bruker.py
pyicoshift/nmrdatatools/general.py
pyicoshift/phasing/__init__.py
pyicoshift/phasing/automics.py
pyicoshift-0.0.3.dist-info/LICENSE
pyicoshift-0.0.3.dist-info/METADATA
pyicoshift-0.0.3.dist-info/WHEEL
pyicoshift-0.0.3.dist-info/top_level.txt
pyicoshift-0.0.3.dist-info/RECORD
