Metadata-Version: 2.1
Name: pyicoshift
Version: 0.0.3
Summary: Python 3 Version of icoshift
Author-email: Sebastian Krossa <sebastian.krossa@ntnu.no>
License: MIT License        
Project-URL: Homepage, https://github.com/sekro/pyicoshift
Project-URL: Bug Tracker, https://github.com/sekro/pyicoshift/issues
Keywords: icoshift,nmr,alignment
Classifier: Programming Language :: Python :: 3
Classifier: License :: OSI Approved :: MIT License
Classifier: Operating System :: OS Independent
Requires-Python: >=3.8
License-File: LICENSE
Requires-Dist: numpy (>=1.23.3)
Requires-Dist: nmrglue (>=0.9)
Requires-Dist: matplotlib (>=3.6.0)
Requires-Dist: scipy (>=1.9.1)
Requires-Dist: scikit-learn (>=1.1.2)
Requires-Dist: statsmodels (>=0.13.2)
